propcache/__init__.py
propcache/_helpers.py
propcache/_helpers_c.pyx
propcache/_helpers_py.py
propcache/py.typed
propcache-0.1.0.dist-info/LICENSE
propcache-0.1.0.dist-info/METADATA
propcache-0.1.0.dist-info/NOTICE
propcache-0.1.0.dist-info/WHEEL
propcache-0.1.0.dist-info/top_level.txt
propcache-0.1.0.dist-info/RECORD
