Metadata-Version: 2.1
Name: propcache
Version: 0.1.0
Summary: Accelerated property cache
Home-page: https://github.com/aio-libs/propcache
Author: Andrew Svetlov
Author-email: andrew.svetlov@gmail.com
Maintainer: aiohttp team <team@aiohttp.org>
Maintainer-email: team@aiohttp.org
License: Apache-2.0
Project-URL: Chat: Matrix, https://matrix.to/#/#aio-libs:matrix.org
Project-URL: Chat: Matrix Space, https://matrix.to/#/#aio-libs-space:matrix.org
Project-URL: CI: GitHub Workflows, https://github.com/aio-libs/propcache/actions?query=branch:master
Project-URL: Code of Conduct, https://github.com/aio-libs/.github/blob/master/CODE_OF_CONDUCT.md
Project-URL: Coverage: codecov, https://codecov.io/github/aio-libs/propcache
Project-URL: Docs: Changelog, https://propcache.readthedocs.io/en/latest/changes/
Project-URL: Docs: RTD, https://propcache.readthedocs.io
Project-URL: GitHub: issues, https://github.com/aio-libs/propcache/issues
Project-URL: GitHub: repo, https://github.com/aio-libs/propcache
Keywords: cython,cext,propcache
Classifier: Development Status :: 5 - Production/Stable
Classifier: Intended Audience :: Developers
Classifier: License :: OSI Approved :: Apache Software License
Classifier: Programming Language :: Cython
Classifier: Programming Language :: Python
Classifier: Programming Language :: Python :: 3
Classifier: Programming Language :: Python :: 3.8
Classifier: Programming Language :: Python :: 3.9
Classifier: Programming Language :: Python :: 3.10
Classifier: Programming Language :: Python :: 3.11
Classifier: Programming Language :: Python :: 3.12
Classifier: Programming Language :: Python :: 3.13
Classifier: Topic :: Internet :: WWW/HTTP
Classifier: Topic :: Software Development :: Libraries :: Python Modules
Requires-Python: >=3.8
License-File: LICENSE
License-File: NOTICE
